[
  {
    "x": 4.96,
    "y": 6.11,
    "pixelX": 420.9147467677651,
    "pixelY": 138.27235831632157,
    "angle": 5.749114556069321,
    "speed": 0.0,
    "time": 0.0,
    "deltaTime": 0.0,
    "interpolationRange": 0.0,
    "color": [
      255,
      0,
      0
    ],
    "index": 0,
    "timeStamp": "1650495434.54468"
  },
  {
    "x": 5.4474278086763075,
    "y": 6.647320133481647,
    "pixelX": 447.5380091377467,
    "pixelY": 108.92398172450663,
    "angle": 3.9982982817725317,
    "speed": 0.0,
    "time": 1.5,
    "deltaTime": 1.5,
    "interpolationRange": 0.2,
    "color": [
      255,
      0,
      0
    ],
    "index": 1,
    "timeStamp": "1650495434.54468"
  },
  {
    "x": 5.986828031145717,
    "y": 7.231795328142381,
    "pixelX": 477.0,
    "pixelY": 77.0,
    "angle": 3.9968039870670147,
    "speed": 0.0,
    "time": 2.5,
    "deltaTime": 1.0,
    "interpolationRange": 0.4,
    "color": [
      255,
      0,
      0
    ],
    "index": 2,
    "timeStamp": "1650495434.54468"
  },
  {
    "x": 6.000211345939933,
    "y": 7.226120578420469,
    "pixelX": 477.73099543112664,
    "pixelY": 77.30995431126655,
    "angle": 3.4962983056007335,
    "speed": 0.0,
    "time": 3.5,
    "deltaTime": 1.0,
    "interpolationRange": 0.2,
    "color": [
      255,
      0,
      0
    ],
    "index": 3,
    "timeStamp": "1650495434.54468"
  }
]