[
  {
    "x": 7.506420467185762,
    "y": 1.6759092324805338,
    "pixelX": 560.0,
    "pixelY": 380.46199086225334,
    "angle": 1.5707963267948966,
    "speed": 0.0,
    "time": 0.0,
    "deltaTime": 0.0,
    "interpolationRange": 0.0,
    "color": [
      255,
      0,
      0
    ],
    "index": 0,
    "timeStamp": "1648326382.089161"
  },
  {
    "x": 7.5,
    "y": 0.7894002224694107,
    "pixelX": 559.6493146689998,
    "pixelY": 428.8830319821133,
    "angle": 1.5707963267948966,
    "speed": 0.0,
    "time": 0.75,
    "deltaTime": 0.75,
    "interpolationRange": 0.15,
    "color": [
      255,
      0,
      0
    ],
    "index": 1,
    "timeStamp": "1648326382.089161"
  },
  {
    "x": 5.926977975528365,
    "y": 2.3702344827586206,
    "pixelX": 473.73099543112664,
    "pixelY": 342.5380091377467,
    "angle": 0.5759586531581288,
    "speed": 0.0,
    "time": 2.5,
    "deltaTime": 1.75,
    "interpolationRange": 0.1,
    "color": [
      255,
      0,
      0
    ],
    "index": 2,
    "timeStamp": "1648326382.089161"
  },
  {
    "x": 5.286185984427141,
    "y": 1.6773010011123468,
    "pixelX": 438.73099543112664,
    "pixelY": 380.38597258676,
    "angle": 0.3923401442155159,
    "speed": 0.0,
    "time": 4.0,
    "deltaTime": 1.5,
    "interpolationRange": 0.0,
    "color": [
      255,
      0,
      0
    ],
    "index": 3,
    "timeStamp": "1648326382.089161"
  }
]